axioms_drf/__init__.py
axioms_drf/_version.py
axioms_drf/authentication.py
axioms_drf/helper.py
axioms_drf/middleware.py
axioms_drf/permissions.py
axioms_drf_py-0.0.11.dist-info/licenses/LICENSE.txt
axioms_drf_py-0.0.11.dist-info/METADATA
axioms_drf_py-0.0.11.dist-info/WHEEL
axioms_drf_py-0.0.11.dist-info/top_level.txt
axioms_drf_py-0.0.11.dist-info/RECORD
