Metadata-Version: 2.4
Name: axioms-drf-py
Version: 0.0.11
Summary: OAuth2/OIDC authentication and authorization for Django REST Framework APIs
Author-email: Abhishek Tiwari <abhishek@abhishek-tiwari.com>
License: MIT
Project-URL: Homepage, https://github.com/abhishektiwari/axioms-drf-py
Project-URL: Documentation, https://axioms-drf-py.abhishek-tiwari.com/
Project-URL: Repository, https://github.com/abhishektiwari/axioms-drf-py
Project-URL: Issues, https://github.com/abhishektiwari/axioms-drf-py/issues
Project-URL: Changelog, https://github.com/abhishektiwari/axioms-drf-py/releases
Keywords: django,djangorestframework,drf,oauth2,oidc,jwt,authentication,authorization,axioms,security
Classifier: Development Status :: 5 - Production/Stable
Classifier: Intended Audience :: Developers
Classifier: License :: OSI Approved :: MIT License
Classifier: Operating System :: OS Independent
Classifier: Programming Language :: Python :: 3
Classifier: Programming Language :: Python :: 3.8
Classifier: Programming Language :: Python :: 3.9
Classifier: Programming Language :: Python :: 3.10
Classifier: Programming Language :: Python :: 3.11
Classifier: Programming Language :: Python :: 3.12
Classifier: Programming Language :: Python :: 3.13
Classifier: Topic :: Software Development :: Libraries :: Python Modules
Classifier: Topic :: Security
Classifier: Framework :: Django
Classifier: Framework :: Django :: 3.2
Classifier: Framework :: Django :: 4.0
Classifier: Framework :: Django :: 4.1
Classifier: Framework :: Django :: 4.2
Classifier: Framework :: Django :: 5.0
Requires-Python: >=3.8
License-File: LICENSE.txt
Requires-Dist: django>=3.2
Requires-Dist: djangorestframework>=3.12.0
Requires-Dist: pyjwt>=2.8.0
Requires-Dist: jwcrypto>=1.5.0
Requires-Dist: python-box>=7.0.0
Requires-Dist: requests<3,>=2.25.0
Requires-Dist: django-environ>=0.9.0
Provides-Extra: dev
Requires-Dist: black>=23.0.0; extra == "dev"
Requires-Dist: ruff>=0.1.0; extra == "dev"
Requires-Dist: pytest>=7.4.0; extra == "dev"
Requires-Dist: pytest-django>=4.5.0; extra == "dev"
Requires-Dist: pytest-cov>=4.1.0; extra == "dev"
Requires-Dist: build>=1.0.0; extra == "dev"
Requires-Dist: twine>=4.0.0; extra == "dev"
Requires-Dist: sphinx>=7.0.0; extra == "dev"
Requires-Dist: sphinx-book-theme>=1.0.0; extra == "dev"
Requires-Dist: sphinx-copybutton>=0.5.0; extra == "dev"
Requires-Dist: sphinx-autobuild>=2021.3.14; extra == "dev"
Provides-Extra: docs
Requires-Dist: sphinx>=7.0.0; extra == "docs"
Requires-Dist: sphinx-book-theme>=1.0.0; extra == "docs"
Requires-Dist: sphinx-copybutton>=0.5.0; extra == "docs"
Requires-Dist: sphinx-autobuild>=2021.3.14; extra == "docs"
Dynamic: license-file
